Workbook

Sheet Planilha1
A1: SAERJ
A3: Usuário | B3: Processador | C3: Memória | D3: Coluna1 | E3: Coluna2
A4: PRISCILA FERNANDES | B4: INTEL I5 650 | C4: 8 GB DDR3 | D4: X | E4: DT
A5: IVANILDE MONTENEGRO | B5: INTEL CORE I5 3470 | C5: 8 GB DDR3 | D5: X | E5: DT
A6: JAQUELINE LESSA | B6: INTEL CORE I5 3470 | C6: 8 GB DDR3 | D6: X | E6: DT
A7: THAMIRES OLIVEIRA | B7: INTEL CORE I5 1334U | C7: 16 GB DDR4 | E7: NB
A8: EVELIN CUNHA | B8: INTEL CORE I5 12400 | C8: 8 GB DDR4 | E8: DT
A9: ISMAEL CAMPELO | B9: INTEL I5 650 | C9: 8 GB DDR3 | D9: X | E9: DT
A10: MARCELO GONÇALVES | B10: INTEL CORE I7 3770 | C10: 8 GB DDR3 | D10: X | E10: DT
A11: FABRICIO MEDEIROS | B11: INTEL CORE I7 1165G7 | C11: 16GB DDR4 | E11: NB
A12: ANDRÉ MANHÃES | B12: INTEL CORE I5 7400 | C12: 16GB DDR4 | E12: DT
A13: FELIPE FACHETTI | B13: INTEL CORE I5 1334U | C13: 16GB DDR4 | E13: NB
A14: ALEXANDRO NASCIMENTO | B14: INTEL CORE I7 1165G7 | C14: 16GB DDR4 | E14: NB
A15: SAC | B15: INTEL CORE I3 2120 | C15: 4GB DDR3 | D15: X | E15: DT
A16: MARCOS CARVALHO | B16: INTEL CORE I5 650 | C16: 8GB DDR3 | D16: X | E16: DT
A17: LUCIA MEDEIROS | B17: INTEL CORE I5 12500 | C17: 8GB DDR4 | E17: DT
A18: LUDMILLA OLIVEIRA | B18: INTEL CORE I7 1355U | C18: 16GB DDR4 | E18: NB
A19: GLAUCIA LORIANO | B19: INTEL CORE I7 1355U | C19: 16GB DDR4 | E19: NB
A20: BENVIDA LUCIA | B20: INTEL CORE I5 13420H | C20: 16GB DDR5 | E20: NB
A21: LARISSA MURCIA | B21: INTEL CORE I7 1355U | C21: 16GB DDR4 | E21: NB
A22: ELIDIANE RODRIGUES | B22: INTEL CORE I5 1334U | C22: 16GB DDR4 | E22: NB
A23: DANIELLE MOITAS | B23: INTEL CORE I5 1334U | C23: 16GB DDR4 | E23: NB
A24: MARCELO REBELO | B24: INTEL CORE I5 1334U | C24: 16GB DDR4 | E24: NB

Sheet Ref Processadores
A1: Tabela de referência – processadores (especificações públicas Intel)
A3: Modelo | B3: Geração Intel | C3: Arquitetura | D3: Ano de lançamento | E3: Segmento
A4: I5 650 | B4: 1 | C4: Clarkdale | D4: 2010 | E4: Desktop
A5: I3 2120 | B5: 2 | C5: Sandy Bridge | D5: 2011 | E5: Desktop
A6: I5 3470 | B6: 3 | C6: Ivy Bridge | D6: 2012 | E6: Desktop
A7: I7 3770 | B7: 3 | C7: Ivy Bridge | D7: 2012 | E7: Desktop
A8: I5 7400 | B8: 7 | C8: Kaby Lake | D8: 2017 | E8: Desktop
A9: I7 1165G7 | B9: 11 | C9: Tiger Lake | D9: 2020 | E9: Notebook
A10: I5 12400 | B10: 12 | C10: Alder Lake | D10: 2022 | E10: Desktop
A11: I5 12500 | B11: 12 | C11: Alder Lake | D11: 2022 | E11: Desktop
A12: I5 1334U | B12: 13 | C12: Raptor Lake | D12: 2023 | E12: Notebook
A13: I7 1355U | B13: 13 | C13: Raptor Lake | D13: 2023 | E13: Notebook
A14: I5 13420H | B14: 13 | C14: Raptor Lake | D14: 2023 | E14: Notebook

Sheet Plano de Modernização
A1: SAERJ – Diagnóstico e Plano de Modernização do Parque de Computadores
A2: Critérios: compatibilidade com Windows 11 (Intel 8ª geração ou superior), memória mínima e idade do processador. Custos são estimativas – validar com cotação.
A4: PREMISSAS | B4: Valor | D4: RESUMO POR FASE | E4: Máquinas | F4: Custo estimado (R$) | G4: Prazo sugerido | H4: Escopo
A5: Ano de referência | B5: 2026 | D5: Fase 1 – Imediata | E5: =COUNTIFS(PlanoMaquinas[Fase],D5) -> 4 | F5: =SUMIFS(PlanoMaquinas[Custo estimado (R$)],PlanoMaquinas[Fase],D5) -> 18000 | G5: Até dez/2026 | H5: Substituir máquinas de 1ª/2ª geração (2010-2011) e/ou com menos de 8 GB – sem suporte Windows 11 e risco de falha
A6: Geração Intel mínima p/ Windows 11 | B6: 8 | D6: Fase 2 – Curto prazo | E6: =COUNTIFS(PlanoMaquinas[Fase],D6) -> 4 | F6: =SUMIFS(PlanoMaquinas[Custo estimado (R$)],PlanoMaquinas[Fase],D6) -> 18000 | G6: 1º trimestre 2027 | H6: Substituir máquinas de 3ª a 7ª geração – incompatíveis com Windows 11
A7: RAM mínima recomendada (GB) | B7: 16 | D7: Fase 3 – Upgrade | E7: =COUNTIFS(PlanoMaquinas[Fase],D7) -> 2 | F7: =SUMIFS(PlanoMaquinas[Custo estimado (R$)],PlanoMaquinas[Fase],D7) -> 500 | G7: Até dez/2026 | H7: Ampliar RAM para 16 GB (DDR4) em máquinas de 12ª geração – baixo custo, alto ganho
A8: Custo desktop novo (R$) | B8: 4500 | D8: Manter | E8: =COUNTIFS(PlanoMaquinas[Fase],D8) -> 11 | F8: =SUMIFS(PlanoMaquinas[Custo estimado (R$)],PlanoMaquinas[Fase],D8) -> 0 | G8: Revisão anual | H8: Máquinas atuais; as de 11ª geração (2020) entram no planejamento de 2027/28
A9: Custo notebook novo (R$) | B9: 5500 | D9: Total | E9: =SUM(E5:E8) -> 21 | F9: =SUM(F5:F8) -> 36500
A10: Custo upgrade +8 GB RAM (R$) | B10: 250
A11: Idade máx. sem monitoramento (anos) | B11: 5 | D11: Máquinas compatíveis c/ Windows 11 | E11: =COUNTIFS(PlanoMaquinas[Compatível Win11],"Sim") -> 13 | F11: =E11/E9 -> 0.61904762
D12: Desktops / Notebooks a substituir | E12: =COUNTIFS(PlanoMaquinas[Ação recomendada],"Substituir",PlanoMaquinas[Tipo],"Desktop") -> 8 | F12: =COUNTIFS(PlanoMaquinas[Ação recomendada],"Substituir",PlanoMaquinas[Tipo],"Notebook") -> 0
A14: Usuário | B14: Tipo | C14: Processador | D14: Memória | E14: Modelo | F14: Geração | G14: Ano lanç. | H14: Idade (anos) | I14: RAM (GB) | J14: Tipo RAM | K14: Compatível Win11 | L14: Ação recomendada | M14: Fase | N14: Custo estimado (R$)
A15: =Planilha1!A4 -> PRISCILA FERNANDES | B15: =IF(Planilha1!E4="DT","Desktop","Notebook") -> Desktop | C15: =Planilha1!B4 -> INTEL I5 650 | D15: =Planilha1!C4 -> 8 GB DDR3 | E15: =TRIM(SUBSTITUTE(SUBSTITUTE(C15,"INTEL CORE ",""),"INTEL ","")) -> I5 650 | F15: =_xlfn.XLOOKUP(E15,RefProc[Modelo],RefProc[Geração Intel]) -> 1 | G15: =_xlfn.XLOOKUP(E15,RefProc[Modelo],RefProc[Ano de lançamento]) -> 2010 | H15: =$B$5-G15 -> 16 | I15: =VALUE(LEFT(D15,SEARCH("GB",D15)-1)) -> 8 | J15: =RIGHT(TRIM(D15),4) -> DDR3 | K15: =IF(F15>=$B$6,"Sim","Não") -> Não | L15: =IF(K15="Não","Substituir",IF(I15<$B$7,"Upgrade de memória",IF(H15>$B$11,"Manter – monitorar","Manter"))) -> Substituir | M15: =IF(L15="Substituir",IF(OR(F15<=2,I15<8),"Fase 1 – Imediata","Fase 2 – Curto prazo"),IF(L15="Upgrade de memória","Fase 3 – Upgrade","Manter")) -> Fase 1 – Imediata | N15: =IF(L15="Substituir",IF(B15="Desktop",$B$8,$B$9),IF(L15="Upgrade de memória",$B$10,0)) -> 4500
A16: =Planilha1!A9 -> ISMAEL CAMPELO | B16: =IF(Planilha1!E9="DT","Desktop","Notebook") -> Desktop | C16: =Planilha1!B9 -> INTEL I5 650 | D16: =Planilha1!C9 -> 8 GB DDR3 | E16: =TRIM(SUBSTITUTE(SUBSTITUTE(C16,"INTEL CORE ",""),"INTEL ","")) -> I5 650 | F16: =_xlfn.XLOOKUP(E16,RefProc[Modelo],RefProc[Geração Intel]) -> 1 | G16: =_xlfn.XLOOKUP(E16,RefProc[Modelo],RefProc[Ano de lançamento]) -> 2010 | H16: =$B$5-G16 -> 16 | I16: =VALUE(LEFT(D16,SEARCH("GB",D16)-1)) -> 8 | J16: =RIGHT(TRIM(D16),4) -> DDR3 | K16: =IF(F16>=$B$6,"Sim","Não") -> Não | L16: =IF(K16="Não","Substituir",IF(I16<$B$7,"Upgrade de memória",IF(H16>$B$11,"Manter – monitorar","Manter"))) -> Substituir | M16: =IF(L16="Substituir",IF(OR(F16<=2,I16<8),"Fase 1 – Imediata","Fase 2 – Curto prazo"),IF(L16="Upgrade de memória","Fase 3 – Upgrade","Manter")) -> Fase 1 – Imediata | N16: =IF(L16="Substituir",IF(B16="Desktop",$B$8,$B$9),IF(L16="Upgrade de memória",$B$10,0)) -> 4500
A17: =Planilha1!A16 -> MARCOS CARVALHO | B17: =IF(Planilha1!E16="DT","Desktop","Notebook") -> Desktop | C17: =Planilha1!B16 -> INTEL CORE I5 650 | D17: =Planilha1!C16 -> 8GB DDR3 | E17: =TRIM(SUBSTITUTE(SUBSTITUTE(C17,"INTEL CORE ",""),"INTEL ","")) -> I5 650 | F17: =_xlfn.XLOOKUP(E17,RefProc[Modelo],RefProc[Geração Intel]) -> 1 | G17: =_xlfn.XLOOKUP(E17,RefProc[Modelo],RefProc[Ano de lançamento]) -> 2010 | H17: =$B$5-G17 -> 16 | I17: =VALUE(LEFT(D17,SEARCH("GB",D17)-1)) -> 8 | J17: =RIGHT(TRIM(D17),4) -> DDR3 | K17: =IF(F17>=$B$6,"Sim","Não") -> Não | L17: =IF(K17="Não","Substituir",IF(I17<$B$7,"Upgrade de memória",IF(H17>$B$11,"Manter – monitorar","Manter"))) -> Substituir | M17: =IF(L17="Substituir",IF(OR(F17<=2,I17<8),"Fase 1 – Imediata","Fase 2 – Curto prazo"),IF(L17="Upgrade de memória","Fase 3 – Upgrade","Manter")) -> Fase 1 – Imediata | N17: =IF(L17="Substituir",IF(B17="Desktop",$B$8,$B$9),IF(L17="Upgrade de memória",$B$10,0)) -> 4500
A18: =Planilha1!A15 -> SAC | B18: =IF(Planilha1!E15="DT","Desktop","Notebook") -> Desktop | C18: =Planilha1!B15 -> INTEL CORE I3 2120 | D18: =Planilha1!C15 -> 4GB DDR3 | E18: =TRIM(SUBSTITUTE(SUBSTITUTE(C18,"INTEL CORE ",""),"INTEL ","")) -> I3 2120 | F18: =_xlfn.XLOOKUP(E18,RefProc[Modelo],RefProc[Geração Intel]) -> 2 | G18: =_xlfn.XLOOKUP(E18,RefProc[Modelo],RefProc[Ano de lançamento]) -> 2011 | H18: =$B$5-G18 -> 15 | I18: =VALUE(LEFT(D18,SEARCH("GB",D18)-1)) -> 4 | J18: =RIGHT(TRIM(D18),4) -> DDR3 | K18: =IF(F18>=$B$6,"Sim","Não") -> Não | L18: =IF(K18="Não","Substituir",IF(I18<$B$7,"Upgrade de memória",IF(H18>$B$11,"Manter – monitorar","Manter"))) -> Substituir | M18: =IF(L18="Substituir",IF(OR(F18<=2,I18<8),"Fase 1 – Imediata","Fase 2 – Curto prazo"),IF(L18="Upgrade de memória","Fase 3 – Upgrade","Manter")) -> Fase 1 – Imediata | N18: =IF(L18="Substituir",IF(B18="Desktop",$B$8,$B$9),IF(L18="Upgrade de memória",$B$10,0)) -> 4500
A19: =Planilha1!A5 -> IVANILDE MONTENEGRO | B19: =IF(Planilha1!E5="DT","Desktop","Notebook") -> Desktop | C19: =Planilha1!B5 -> INTEL CORE I5 3470 | D19: =Planilha1!C5 -> 8 GB DDR3 | E19: =TRIM(SUBSTITUTE(SUBSTITUTE(C19,"INTEL CORE ",""),"INTEL ","")) -> I5 3470 | F19: =_xlfn.XLOOKUP(E19,RefProc[Modelo],RefProc[Geração Intel]) -> 3 | G19: =_xlfn.XLOOKUP(E19,RefProc[Modelo],RefProc[Ano de lançamento]) -> 2012 | H19: =$B$5-G19 -> 14 | I19: =VALUE(LEFT(D19,SEARCH("GB",D19)-1)) -> 8 | J19: =RIGHT(TRIM(D19),4) -> DDR3 | K19: =IF(F19>=$B$6,"Sim","Não") -> Não | L19: =IF(K19="Não","Substituir",IF(I19<$B$7,"Upgrade de memória",IF(H19>$B$11,"Manter – monitorar","Manter"))) -> Substituir | M19: =IF(L19="Substituir",IF(OR(F19<=2,I19<8),"Fase 1 – Imediata","Fase 2 – Curto prazo"),IF(L19="Upgrade de memória","Fase 3 – Upgrade","Manter")) -> Fase 2 – Curto prazo | N19: =IF(L19="Substituir",IF(B19="Desktop",$B$8,$B$9),IF(L19="Upgrade de memória",$B$10,0)) -> 4500
A20: =Planilha1!A6 -> JAQUELINE LESSA | B20: =IF(Planilha1!E6="DT","Desktop","Notebook") -> Desktop | C20: =Planilha1!B6 -> INTEL CORE I5 3470 | D20: =Planilha1!C6 -> 8 GB DDR3 | E20: =TRIM(SUBSTITUTE(SUBSTITUTE(C20,"INTEL CORE ",""),"INTEL ","")) -> I5 3470 | F20: =_xlfn.XLOOKUP(E20,RefProc[Modelo],RefProc[Geração Intel]) -> 3 | G20: =_xlfn.XLOOKUP(E20,RefProc[Modelo],RefProc[Ano de lançamento]) -> 2012 | H20: =$B$5-G20 -> 14 | I20: =VALUE(LEFT(D20,SEARCH("GB",D20)-1)) -> 8 | J20: =RIGHT(TRIM(D20),4) -> DDR3 | K20: =IF(F20>=$B$6,"Sim","Não") -> Não | L20: =IF(K20="Não","Substituir",IF(I20<$B$7,"Upgrade de memória",IF(H20>$B$11,"Manter – monitorar","Manter"))) -> Substituir | M20: =IF(L20="Substituir",IF(OR(F20<=2,I20<8),"Fase 1 – Imediata","Fase 2 – Curto prazo"),IF(L20="Upgrade de memória","Fase 3 – Upgrade","Manter")) -> Fase 2 – Curto prazo | N20: =IF(L20="Substituir",IF(B20="Desktop",$B$8,$B$9),IF(L20="Upgrade de memória",$B$10,0)) -> 4500
A21: =Planilha1!A10 -> MARCELO GONÇALVES | B21: =IF(Planilha1!E10="DT","Desktop","Notebook") -> Desktop | C21: =Planilha1!B10 -> INTEL CORE I7 3770 | D21: =Planilha1!C10 -> 8 GB DDR3 | E21: =TRIM(SUBSTITUTE(SUBSTITUTE(C21,"INTEL CORE ",""),"INTEL ","")) -> I7 3770 | F21: =_xlfn.XLOOKUP(E21,RefProc[Modelo],RefProc[Geração Intel]) -> 3 | G21: =_xlfn.XLOOKUP(E21,RefProc[Modelo],RefProc[Ano de lançamento]) -> 2012 | H21: =$B$5-G21 -> 14 | I21: =VALUE(LEFT(D21,SEARCH("GB",D21)-1)) -> 8 | J21: =RIGHT(TRIM(D21),4) -> DDR3 | K21: =IF(F21>=$B$6,"Sim","Não") -> Não | L21: =IF(K21="Não","Substituir",IF(I21<$B$7,"Upgrade de memória",IF(H21>$B$11,"Manter – monitorar","Manter"))) -> Substituir | M21: =IF(L21="Substituir",IF(OR(F21<=2,I21<8),"Fase 1 – Imediata","Fase 2 – Curto prazo"),IF(L21="Upgrade de memória","Fase 3 – Upgrade","Manter")) -> Fase 2 – Curto prazo | N21: =IF(L21="Substituir",IF(B21="Desktop",$B$8,$B$9),IF(L21="Upgrade de memória",$B$10,0)) -> 4500
A22: =Planilha1!A12 -> ANDRÉ MANHÃES | B22: =IF(Planilha1!E12="DT","Desktop","Notebook") -> Desktop | C22: =Planilha1!B12 -> INTEL CORE I5 7400 | D22: =Planilha1!C12 -> 16GB DDR4 | E22: =TRIM(SUBSTITUTE(SUBSTITUTE(C22,"INTEL CORE ",""),"INTEL ","")) -> I5 7400 | F22: =_xlfn.XLOOKUP(E22,RefProc[Modelo],RefProc[Geração Intel]) -> 7 | G22: =_xlfn.XLOOKUP(E22,RefProc[Modelo],RefProc[Ano de lançamento]) -> 2017 | H22: =$B$5-G22 -> 9 | I22: =VALUE(LEFT(D22,SEARCH("GB",D22)-1)) -> 16 | J22: =RIGHT(TRIM(D22),4) -> DDR4 | K22: =IF(F22>=$B$6,"Sim","Não") -> Não | L22: =IF(K22="Não","Substituir",IF(I22<$B$7,"Upgrade de memória",IF(H22>$B$11,"Manter – monitorar","Manter"))) -> Substituir | M22: =IF(L22="Substituir",IF(OR(F22<=2,I22<8),"Fase 1 – Imediata","Fase 2 – Curto prazo"),IF(L22="Upgrade de memória","Fase 3 – Upgrade","Manter")) -> Fase 2 – Curto prazo | N22: =IF(L22="Substituir",IF(B22="Desktop",$B$8,$B$9),IF(L22="Upgrade de memória",$B$10,0)) -> 4500
A23: =Planilha1!A11 -> FABRICIO MEDEIROS | B23: =IF(Planilha1!E11="DT","Desktop","Notebook") -> Notebook | C23: =Planilha1!B11 -> INTEL CORE I7 1165G7 | D23: =Planilha1!C11 -> 16GB DDR4 | E23: =TRIM(SUBSTITUTE(SUBSTITUTE(C23,"INTEL CORE ",""),"INTEL ","")) -> I7 1165G7 | F23: =_xlfn.XLOOKUP(E23,RefProc[Modelo],RefProc[Geração Intel]) -> 11 | G23: =_xlfn.XLOOKUP(E23,RefProc[Modelo],RefProc[Ano de lançamento]) -> 2020 | H23: =$B$5-G23 -> 6 | I23: =VALUE(LEFT(D23,SEARCH("GB",D23)-1)) -> 16 | J23: =RIGHT(TRIM(D23),4) -> DDR4 | K23: =IF(F23>=$B$6,"Sim","Não") -> Sim | L23: =IF(K23="Não","Substituir",IF(I23<$B$7,"Upgrade de memória",IF(H23>$B$11,"Manter – monitorar","Manter"))) -> Manter – monitorar | M23: =IF(L23="Substituir",IF(OR(F23<=2,I23<8),"Fase 1 – Imediata","Fase 2 – Curto prazo"),IF(L23="Upgrade de memória","Fase 3 – Upgrade","Manter")) -> Manter | N23: =IF(L23="Substituir",IF(B23="Desktop",$B$8,$B$9),IF(L23="Upgrade de memória",$B$10,0)) -> 0
A24: =Planilha1!A14 -> ALEXANDRO NASCIMENTO | B24: =IF(Planilha1!E14="DT","Desktop","Notebook") -> Notebook | C24: =Planilha1!B14 -> INTEL CORE I7 1165G7 | D24: =Planilha1!C14 -> 16GB DDR4 | E24: =TRIM(SUBSTITUTE(SUBSTITUTE(C24,"INTEL CORE ",""),"INTEL ","")) -> I7 1165G7 | F24: =_xlfn.XLOOKUP(E24,RefProc[Modelo],RefProc[Geração Intel]) -> 11 | G24: =_xlfn.XLOOKUP(E24,RefProc[Modelo],RefProc[Ano de lançamento]) -> 2020 | H24: =$B$5-G24 -> 6 | I24: =VALUE(LEFT(D24,SEARCH("GB",D24)-1)) -> 16 | J24: =RIGHT(TRIM(D24),4) -> DDR4 | K24: =IF(F24>=$B$6,"Sim","Não") -> Sim | L24: =IF(K24="Não","Substituir",IF(I24<$B$7,"Upgrade de memória",IF(H24>$B$11,"Manter – monitorar","Manter"))) -> Manter – monitorar | M24: =IF(L24="Substituir",IF(OR(F24<=2,I24<8),"Fase 1 – Imediata","Fase 2 – Curto prazo"),IF(L24="Upgrade de memória","Fase 3 – Upgrade","Manter")) -> Manter | N24: =IF(L24="Substituir",IF(B24="Desktop",$B$8,$B$9),IF(L24="Upgrade de memória",$B$10,0)) -> 0
A25: =Planilha1!A8 -> EVELIN CUNHA | B25: =IF(Planilha1!E8="DT","Desktop","Notebook") -> Desktop | C25: =Planilha1!B8 -> INTEL CORE I5 12400 | D25: =Planilha1!C8 -> 8 GB DDR4 | E25: =TRIM(SUBSTITUTE(SUBSTITUTE(C25,"INTEL CORE ",""),"INTEL ","")) -> I5 12400 | F25: =_xlfn.XLOOKUP(E25,RefProc[Modelo],RefProc[Geração Intel]) -> 12 | G25: =_xlfn.XLOOKUP(E25,RefProc[Modelo],RefProc[Ano de lançamento]) -> 2022 | H25: =$B$5-G25 -> 4 | I25: =VALUE(LEFT(D25,SEARCH("GB",D25)-1)) -> 8 | J25: =RIGHT(TRIM(D25),4) -> DDR4 | K25: =IF(F25>=$B$6,"Sim","Não") -> Sim | L25: =IF(K25="Não","Substituir",IF(I25<$B$7,"Upgrade de memória",IF(H25>$B$11,"Manter – monitorar","Manter"))) -> Upgrade de memória | M25: =IF(L25="Substituir",IF(OR(F25<=2,I25<8),"Fase 1 – Imediata","Fase 2 – Curto prazo"),IF(L25="Upgrade de memória","Fase 3 – Upgrade","Manter")) -> Fase 3 – Upgrade | N25: =IF(L25="Substituir",IF(B25="Desktop",$B$8,$B$9),IF(L25="Upgrade de memória",$B$10,0)) -> 250
A26: =Planilha1!A17 -> LUCIA MEDEIROS | B26: =IF(Planilha1!E17="DT","Desktop","Notebook") -> Desktop | C26: =Planilha1!B17 -> INTEL CORE I5 12500 | D26: =Planilha1!C17 -> 8GB DDR4 | E26: =TRIM(SUBSTITUTE(SUBSTITUTE(C26,"INTEL CORE ",""),"INTEL ","")) -> I5 12500 | F26: =_xlfn.XLOOKUP(E26,RefProc[Modelo],RefProc[Geração Intel]) -> 12 | G26: =_xlfn.XLOOKUP(E26,RefProc[Modelo],RefProc[Ano de lançamento]) -> 2022 | H26: =$B$5-G26 -> 4 | I26: =VALUE(LEFT(D26,SEARCH("GB",D26)-1)) -> 8 | J26: =RIGHT(TRIM(D26),4) -> DDR4 | K26: =IF(F26>=$B$6,"Sim","Não") -> Sim | L26: =IF(K26="Não","Substituir",IF(I26<$B$7,"Upgrade de memória",IF(H26>$B$11,"Manter – monitorar","Manter"))) -> Upgrade de memória | M26: =IF(L26="Substituir",IF(OR(F26<=2,I26<8),"Fase 1 – Imediata","Fase 2 – Curto prazo"),IF(L26="Upgrade de memória","Fase 3 – Upgrade","Manter")) -> Fase 3 – Upgrade | N26: =IF(L26="Substituir",IF(B26="Desktop",$B$8,$B$9),IF(L26="Upgrade de memória",$B$10,0)) -> 250
A27: =Planilha1!A7 -> THAMIRES OLIVEIRA | B27: =IF(Planilha1!E7="DT","Desktop","Notebook") -> Notebook | C27: =Planilha1!B7 -> INTEL CORE I5 1334U | D27: =Planilha1!C7 -> 16 GB DDR4 | E27: =TRIM(SUBSTITUTE(SUBSTITUTE(C27,"INTEL CORE ",""),"INTEL ","")) -> I5 1334U | F27: =_xlfn.XLOOKUP(E27,RefProc[Modelo],RefProc[Geração Intel]) -> 13 | G27: =_xlfn.XLOOKUP(E27,RefProc[Modelo],RefProc[Ano de lançamento]) -> 2023 | H27: =$B$5-G27 -> 3 | I27: =VALUE(LEFT(D27,SEARCH("GB",D27)-1)) -> 16 | J27: =RIGHT(TRIM(D27),4) -> DDR4 | K27: =IF(F27>=$B$6,"Sim","Não") -> Sim | L27: =IF(K27="Não","Substituir",IF(I27<$B$7,"Upgrade de memória",IF(H27>$B$11,"Manter – monitorar","Manter"))) -> Manter | M27: =IF(L27="Substituir",IF(OR(F27<=2,I27<8),"Fase 1 – Imediata","Fase 2 – Curto prazo"),IF(L27="Upgrade de memória","Fase 3 – Upgrade","Manter")) -> Manter | N27: =IF(L27="Substituir",IF(B27="Desktop",$B$8,$B$9),IF(L27="Upgrade de memória",$B$10,0)) -> 0
A28: =Planilha1!A13 -> FELIPE FACHETTI | B28: =IF(Planilha1!E13="DT","Desktop","Notebook") -> Notebook | C28: =Planilha1!B13 -> INTEL CORE I5 1334U | D28: =Planilha1!C13 -> 16GB DDR4 | E28: =TRIM(SUBSTITUTE(SUBSTITUTE(C28,"INTEL CORE ",""),"INTEL ","")) -> I5 1334U | F28: =_xlfn.XLOOKUP(E28,RefProc[Modelo],RefProc[Geração Intel]) -> 13 | G28: =_xlfn.XLOOKUP(E28,RefProc[Modelo],RefProc[Ano de lançamento]) -> 2023 | H28: =$B$5-G28 -> 3 | I28: =VALUE(LEFT(D28,SEARCH("GB",D28)-1)) -> 16 | J28: =RIGHT(TRIM(D28),4) -> DDR4 | K28: =IF(F28>=$B$6,"Sim","Não") -> Sim | L28: =IF(K28="Não","Substituir",IF(I28<$B$7,"Upgrade de memória",IF(H28>$B$11,"Manter – monitorar","Manter"))) -> Manter | M28: =IF(L28="Substituir",IF(OR(F28<=2,I28<8),"Fase 1 – Imediata","Fase 2 – Curto prazo"),IF(L28="Upgrade de memória","Fase 3 – Upgrade","Manter")) -> Manter | N28: =IF(L28="Substituir",IF(B28="Desktop",$B$8,$B$9),IF(L28="Upgrade de memória",$B$10,0)) -> 0
A29: =Planilha1!A18 -> LUDMILLA OLIVEIRA | B29: =IF(Planilha1!E18="DT","Desktop","Notebook") -> Notebook | C29: =Planilha1!B18 -> INTEL CORE I7 1355U | D29: =Planilha1!C18 -> 16GB DDR4 | E29: =TRIM(SUBSTITUTE(SUBSTITUTE(C29,"INTEL CORE ",""),"INTEL ","")) -> I7 1355U | F29: =_xlfn.XLOOKUP(E29,RefProc[Modelo],RefProc[Geração Intel]) -> 13 | G29: =_xlfn.XLOOKUP(E29,RefProc[Modelo],RefProc[Ano de lançamento]) -> 2023 | H29: =$B$5-G29 -> 3 | I29: =VALUE(LEFT(D29,SEARCH("GB",D29)-1)) -> 16 | J29: =RIGHT(TRIM(D29),4) -> DDR4 | K29: =IF(F29>=$B$6,"Sim","Não") -> Sim | L29: =IF(K29="Não","Substituir",IF(I29<$B$7,"Upgrade de memória",IF(H29>$B$11,"Manter – monitorar","Manter"))) -> Manter | M29: =IF(L29="Substituir",IF(OR(F29<=2,I29<8),"Fase 1 – Imediata","Fase 2 – Curto prazo"),IF(L29="Upgrade de memória","Fase 3 – Upgrade","Manter")) -> Manter | N29: =IF(L29="Substituir",IF(B29="Desktop",$B$8,$B$9),IF(L29="Upgrade de memória",$B$10,0)) -> 0
A30: =Planilha1!A19 -> GLAUCIA LORIANO | B30: =IF(Planilha1!E19="DT","Desktop","Notebook") -> Notebook | C30: =Planilha1!B19 -> INTEL CORE I7 1355U | D30: =Planilha1!C19 -> 16GB DDR4 | E30: =TRIM(SUBSTITUTE(SUBSTITUTE(C30,"INTEL CORE ",""),"INTEL ","")) -> I7 1355U | F30: =_xlfn.XLOOKUP(E30,RefProc[Modelo],RefProc[Geração Intel]) -> 13 | G30: =_xlfn.XLOOKUP(E30,RefProc[Modelo],RefProc[Ano de lançamento]) -> 2023 | H30: =$B$5-G30 -> 3 | I30: =VALUE(LEFT(D30,SEARCH("GB",D30)-1)) -> 16 | J30: =RIGHT(TRIM(D30),4) -> DDR4 | K30: =IF(F30>=$B$6,"Sim","Não") -> Sim | L30: =IF(K30="Não","Substituir",IF(I30<$B$7,"Upgrade de memória",IF(H30>$B$11,"Manter – monitorar","Manter"))) -> Manter | M30: =IF(L30="Substituir",IF(OR(F30<=2,I30<8),"Fase 1 – Imediata","Fase 2 – Curto prazo"),IF(L30="Upgrade de memória","Fase 3 – Upgrade","Manter")) -> Manter | N30: =IF(L30="Substituir",IF(B30="Desktop",$B$8,$B$9),IF(L30="Upgrade de memória",$B$10,0)) -> 0
A31: =Planilha1!A20 -> BENVIDA LUCIA | B31: =IF(Planilha1!E20="DT","Desktop","Notebook") -> Notebook | C31: =Planilha1!B20 -> INTEL CORE I5 13420H | D31: =Planilha1!C20 -> 16GB DDR5 | E31: =TRIM(SUBSTITUTE(SUBSTITUTE(C31,"INTEL CORE ",""),"INTEL ","")) -> I5 13420H | F31: =_xlfn.XLOOKUP(E31,RefProc[Modelo],RefProc[Geração Intel]) -> 13 | G31: =_xlfn.XLOOKUP(E31,RefProc[Modelo],RefProc[Ano de lançamento]) -> 2023 | H31: =$B$5-G31 -> 3 | I31: =VALUE(LEFT(D31,SEARCH("GB",D31)-1)) -> 16 | J31: =RIGHT(TRIM(D31),4) -> DDR5 | K31: =IF(F31>=$B$6,"Sim","Não") -> Sim | L31: =IF(K31="Não","Substituir",IF(I31<$B$7,"Upgrade de memória",IF(H31>$B$11,"Manter – monitorar","Manter"))) -> Manter | M31: =IF(L31="Substituir",IF(OR(F31<=2,I31<8),"Fase 1 – Imediata","Fase 2 – Curto prazo"),IF(L31="Upgrade de memória","Fase 3 – Upgrade","Manter")) -> Manter | N31: =IF(L31="Substituir",IF(B31="Desktop",$B$8,$B$9),IF(L31="Upgrade de memória",$B$10,0)) -> 0
A32: =Planilha1!A21 -> LARISSA MURCIA | B32: =IF(Planilha1!E21="DT","Desktop","Notebook") -> Notebook | C32: =Planilha1!B21 -> INTEL CORE I7 1355U | D32: =Planilha1!C21 -> 16GB DDR4 | E32: =TRIM(SUBSTITUTE(SUBSTITUTE(C32,"INTEL CORE ",""),"INTEL ","")) -> I7 1355U | F32: =_xlfn.XLOOKUP(E32,RefProc[Modelo],RefProc[Geração Intel]) -> 13 | G32: =_xlfn.XLOOKUP(E32,RefProc[Modelo],RefProc[Ano de lançamento]) -> 2023 | H32: =$B$5-G32 -> 3 | I32: =VALUE(LEFT(D32,SEARCH("GB",D32)-1)) -> 16 | J32: =RIGHT(TRIM(D32),4) -> DDR4 | K32: =IF(F32>=$B$6,"Sim","Não") -> Sim | L32: =IF(K32="Não","Substituir",IF(I32<$B$7,"Upgrade de memória",IF(H32>$B$11,"Manter – monitorar","Manter"))) -> Manter | M32: =IF(L32="Substituir",IF(OR(F32<=2,I32<8),"Fase 1 – Imediata","Fase 2 – Curto prazo"),IF(L32="Upgrade de memória","Fase 3 – Upgrade","Manter")) -> Manter | N32: =IF(L32="Substituir",IF(B32="Desktop",$B$8,$B$9),IF(L32="Upgrade de memória",$B$10,0)) -> 0
A33: =Planilha1!A22 -> ELIDIANE RODRIGUES | B33: =IF(Planilha1!E22="DT","Desktop","Notebook") -> Notebook | C33: =Planilha1!B22 -> INTEL CORE I5 1334U | D33: =Planilha1!C22 -> 16GB DDR4 | E33: =TRIM(SUBSTITUTE(SUBSTITUTE(C33,"INTEL CORE ",""),"INTEL ","")) -> I5 1334U | F33: =_xlfn.XLOOKUP(E33,RefProc[Modelo],RefProc[Geração Intel]) -> 13 | G33: =_xlfn.XLOOKUP(E33,RefProc[Modelo],RefProc[Ano de lançamento]) -> 2023 | H33: =$B$5-G33 -> 3 | I33: =VALUE(LEFT(D33,SEARCH("GB",D33)-1)) -> 16 | J33: =RIGHT(TRIM(D33),4) -> DDR4 | K33: =IF(F33>=$B$6,"Sim","Não") -> Sim | L33: =IF(K33="Não","Substituir",IF(I33<$B$7,"Upgrade de memória",IF(H33>$B$11,"Manter – monitorar","Manter"))) -> Manter | M33: =IF(L33="Substituir",IF(OR(F33<=2,I33<8),"Fase 1 – Imediata","Fase 2 – Curto prazo"),IF(L33="Upgrade de memória","Fase 3 – Upgrade","Manter")) -> Manter | N33: =IF(L33="Substituir",IF(B33="Desktop",$B$8,$B$9),IF(L33="Upgrade de memória",$B$10,0)) -> 0
A34: =Planilha1!A23 -> DANIELLE MOITAS | B34: =IF(Planilha1!E23="DT","Desktop","Notebook") -> Notebook | C34: =Planilha1!B23 -> INTEL CORE I5 1334U | D34: =Planilha1!C23 -> 16GB DDR4 | E34: =TRIM(SUBSTITUTE(SUBSTITUTE(C34,"INTEL CORE ",""),"INTEL ","")) -> I5 1334U | F34: =_xlfn.XLOOKUP(E34,RefProc[Modelo],RefProc[Geração Intel]) -> 13 | G34: =_xlfn.XLOOKUP(E34,RefProc[Modelo],RefProc[Ano de lançamento]) -> 2023 | H34: =$B$5-G34 -> 3 | I34: =VALUE(LEFT(D34,SEARCH("GB",D34)-1)) -> 16 | J34: =RIGHT(TRIM(D34),4) -> DDR4 | K34: =IF(F34>=$B$6,"Sim","Não") -> Sim | L34: =IF(K34="Não","Substituir",IF(I34<$B$7,"Upgrade de memória",IF(H34>$B$11,"Manter – monitorar","Manter"))) -> Manter | M34: =IF(L34="Substituir",IF(OR(F34<=2,I34<8),"Fase 1 – Imediata","Fase 2 – Curto prazo"),IF(L34="Upgrade de memória","Fase 3 – Upgrade","Manter")) -> Manter | N34: =IF(L34="Substituir",IF(B34="Desktop",$B$8,$B$9),IF(L34="Upgrade de memória",$B$10,0)) -> 0
A35: =Planilha1!A24 -> MARCELO REBELO | B35: =IF(Planilha1!E24="DT","Desktop","Notebook") -> Notebook | C35: =Planilha1!B24 -> INTEL CORE I5 1334U | D35: =Planilha1!C24 -> 16GB DDR4 | E35: =TRIM(SUBSTITUTE(SUBSTITUTE(C35,"INTEL CORE ",""),"INTEL ","")) -> I5 1334U | F35: =_xlfn.XLOOKUP(E35,RefProc[Modelo],RefProc[Geração Intel]) -> 13 | G35: =_xlfn.XLOOKUP(E35,RefProc[Modelo],RefProc[Ano de lançamento]) -> 2023 | H35: =$B$5-G35 -> 3 | I35: =VALUE(LEFT(D35,SEARCH("GB",D35)-1)) -> 16 | J35: =RIGHT(TRIM(D35),4) -> DDR4 | K35: =IF(F35>=$B$6,"Sim","Não") -> Sim | L35: =IF(K35="Não","Substituir",IF(I35<$B$7,"Upgrade de memória",IF(H35>$B$11,"Manter – monitorar","Manter"))) -> Manter | M35: =IF(L35="Substituir",IF(OR(F35<=2,I35<8),"Fase 1 – Imediata","Fase 2 – Curto prazo"),IF(L35="Upgrade de memória","Fase 3 – Upgrade","Manter")) -> Manter | N35: =IF(L35="Substituir",IF(B35="Desktop",$B$8,$B$9),IF(L35="Upgrade de memória",$B$10,0)) -> 0
A38: RECOMENDAÇÕES DO PLANO
A39: 1. Padrão de aquisição – Desktop | B39: Intel Core i5 14ª ger. ou Core Ultra 5, 16 GB DDR5, SSD NVMe 512 GB, Windows 11 Pro, garantia on-site de 3 anos
A40: 2. Padrão de aquisição – Notebook | B40: Intel Core Ultra 5 / i5 13ª ger. ou superior, 16 GB, SSD NVMe 512 GB, Windows 11 Pro, garantia de 3 anos
A41: 3. Sistema operacional | B41: O suporte do Windows 10 terminou em out/2025: migrar todas as máquinas compatíveis para Windows 11 e priorizar a troca das incompatíveis
A42: 4. Armazenamento | B42: Verificar se as máquinas mantidas usam SSD; trocar HDs por SSD (baixo custo, grande ganho de desempenho)
A43: 5. Aproveitamento | B43: Máquinas substituídas não devem voltar à rede; fazer backup, apagar os discos com segurança e dar destino ambientalmente correto (e-lixo)
A44: 6. Ciclo de renovação | B44: Adotar ciclo de 5 anos: revisar anualmente esta planilha (ano de referência em B5) e orçar a renovação das máquinas de 11ª geração para 2027/28

Sheet Reaproveitamento
A1: SAERJ – Reaproveitamento das Máquinas Substituídas
A2: Máquinas incompatíveis com Windows 11 (Fases 1 e 2 do plano). Reaproveitar somente com SO suportado e SSD. Custos são estimativas – validar com cotação.
A4: PREMISSAS | B4: Valor | D4: RESUMO | E4: Máquinas | F4: Custo preparação (R$)
A5: Custo SSD 480/512 GB + instalação (R$) | B5: 200 | D5: Reaproveitar | E5: =COUNTIFS(Reaproveitamento[Recomendação],D5) -> 1 | F5: =SUMIFS(Reaproveitamento[Custo preparação (R$)],Reaproveitamento[Recomendação],D5) -> 200
D6: Reaproveitar (condicional) | E6: =COUNTIFS(Reaproveitamento[Recomendação],D6) -> 2 | F6: =SUMIFS(Reaproveitamento[Custo preparação (R$)],Reaproveitamento[Recomendação],D6) -> 400
D7: Reposição de peças | E7: =COUNTIFS(Reaproveitamento[Recomendação],D7) -> 1 | F7: =SUMIFS(Reaproveitamento[Custo preparação (R$)],Reaproveitamento[Recomendação],D7) -> 0
D8: Descartar | E8: =COUNTIFS(Reaproveitamento[Recomendação],D8) -> 4 | F8: =SUMIFS(Reaproveitamento[Custo preparação (R$)],Reaproveitamento[Recomendação],D8) -> 0
D9: Total | E9: =SUM(E5:E8) -> 8 | F9: =SUM(F5:F8) -> 600
A11: Usuário atual | B11: Tipo | C11: Processador | D11: Memória | E11: Ano lanç. | F11: Idade (anos) | G11: Recomendação | H11: Possível uso | I11: Sistema operacional sugerido | J11: Justificativa | K11: Custo preparação (R$)
A12: ANDRÉ MANHÃES | B12: =_xlfn.XLOOKUP($A12,PlanoMaquinas[Usuário],PlanoMaquinas[Tipo]) -> Desktop | C12: =_xlfn.XLOOKUP($A12,PlanoMaquinas[Usuário],PlanoMaquinas[Processador]) -> INTEL CORE I5 7400 | D12: =_xlfn.XLOOKUP($A12,PlanoMaquinas[Usuário],PlanoMaquinas[Memória]) -> 16GB DDR4 | E12: =_xlfn.XLOOKUP($A12,PlanoMaquinas[Usuário],PlanoMaquinas[Ano lanç.]) -> 2017 | F12: =_xlfn.XLOOKUP($A12,PlanoMaquinas[Usuário],PlanoMaquinas[Idade (anos)]) -> 9 | G12: Reaproveitar | H12: Máquina reserva, sala de treinamento, estação de digitalização/impressão ou terminal de consulta | I12: ChromeOS Flex / Linux (ou Windows 10 com ESU até out/2028) | J12: Melhor candidata: 16 GB DDR4 e processador de 7ª geração ainda com bom desempenho | K12: =IF(LEFT(G12,12)="Reaproveitar",$B$5,0) -> 200
A13: MARCELO GONÇALVES | B13: =_xlfn.XLOOKUP($A13,PlanoMaquinas[Usuário],PlanoMaquinas[Tipo]) -> Desktop | C13: =_xlfn.XLOOKUP($A13,PlanoMaquinas[Usuário],PlanoMaquinas[Processador]) -> INTEL CORE I7 3770 | D13: =_xlfn.XLOOKUP($A13,PlanoMaquinas[Usuário],PlanoMaquinas[Memória]) -> 8 GB DDR3 | E13: =_xlfn.XLOOKUP($A13,PlanoMaquinas[Usuário],PlanoMaquinas[Ano lanç.]) -> 2012 | F13: =_xlfn.XLOOKUP($A13,PlanoMaquinas[Usuário],PlanoMaquinas[Idade (anos)]) -> 14 | G13: Reaproveitar (condicional) | H13: Painel informativo em TV, totem de senhas/consulta, navegação simples | I13: ChromeOS Flex / Linux | J13: i7 3770 é o melhor processador entre os antigos; reaproveitar só se houver função definida | K13: =IF(LEFT(G13,12)="Reaproveitar",$B$5,0) -> 200
A14: IVANILDE MONTENEGRO | B14: =_xlfn.XLOOKUP($A14,PlanoMaquinas[Usuário],PlanoMaquinas[Tipo]) -> Desktop | C14: =_xlfn.XLOOKUP($A14,PlanoMaquinas[Usuário],PlanoMaquinas[Processador]) -> INTEL CORE I5 3470 | D14: =_xlfn.XLOOKUP($A14,PlanoMaquinas[Usuário],PlanoMaquinas[Memória]) -> 8 GB DDR3 | E14: =_xlfn.XLOOKUP($A14,PlanoMaquinas[Usuário],PlanoMaquinas[Ano lanç.]) -> 2012 | F14: =_xlfn.XLOOKUP($A14,PlanoMaquinas[Usuário],PlanoMaquinas[Idade (anos)]) -> 14 | G14: Reaproveitar (condicional) | H14: Mesmos usos de baixa exigência (painel, totem, consulta) | I14: ChromeOS Flex / Linux | J14: Aproveitar no máximo uma das duas máquinas i5 3470 | K14: =IF(LEFT(G14,12)="Reaproveitar",$B$5,0) -> 200
A15: JAQUELINE LESSA | B15: =_xlfn.XLOOKUP($A15,PlanoMaquinas[Usuário],PlanoMaquinas[Tipo]) -> Desktop | C15: =_xlfn.XLOOKUP($A15,PlanoMaquinas[Usuário],PlanoMaquinas[Processador]) -> INTEL CORE I5 3470 | D15: =_xlfn.XLOOKUP($A15,PlanoMaquinas[Usuário],PlanoMaquinas[Memória]) -> 8 GB DDR3 | E15: =_xlfn.XLOOKUP($A15,PlanoMaquinas[Usuário],PlanoMaquinas[Ano lanç.]) -> 2012 | F15: =_xlfn.XLOOKUP($A15,PlanoMaquinas[Usuário],PlanoMaquinas[Idade (anos)]) -> 14 | G15: Reposição de peças | H15: Fonte, memória DDR3 e periféricos como reserva para as máquinas reaproveitadas | I15: — | J15: Segunda i5 3470: mais útil como fonte de peças | K15: =IF(LEFT(G15,12)="Reaproveitar",$B$5,0) -> 0
A16: PRISCILA FERNANDES | B16: =_xlfn.XLOOKUP($A16,PlanoMaquinas[Usuário],PlanoMaquinas[Tipo]) -> Desktop | C16: =_xlfn.XLOOKUP($A16,PlanoMaquinas[Usuário],PlanoMaquinas[Processador]) -> INTEL I5 650 | D16: =_xlfn.XLOOKUP($A16,PlanoMaquinas[Usuário],PlanoMaquinas[Memória]) -> 8 GB DDR3 | E16: =_xlfn.XLOOKUP($A16,PlanoMaquinas[Usuário],PlanoMaquinas[Ano lanç.]) -> 2010 | F16: =_xlfn.XLOOKUP($A16,PlanoMaquinas[Usuário],PlanoMaquinas[Idade (anos)]) -> 16 | G16: Descartar | H16: — | I16: — | J16: i5 650 (2010): alto consumo de energia, hardware com 16 anos e risco de falha | K16: =IF(LEFT(G16,12)="Reaproveitar",$B$5,0) -> 0
A17: ISMAEL CAMPELO | B17: =_xlfn.XLOOKUP($A17,PlanoMaquinas[Usuário],PlanoMaquinas[Tipo]) -> Desktop | C17: =_xlfn.XLOOKUP($A17,PlanoMaquinas[Usuário],PlanoMaquinas[Processador]) -> INTEL I5 650 | D17: =_xlfn.XLOOKUP($A17,PlanoMaquinas[Usuário],PlanoMaquinas[Memória]) -> 8 GB DDR3 | E17: =_xlfn.XLOOKUP($A17,PlanoMaquinas[Usuário],PlanoMaquinas[Ano lanç.]) -> 2010 | F17: =_xlfn.XLOOKUP($A17,PlanoMaquinas[Usuário],PlanoMaquinas[Idade (anos)]) -> 16 | G17: Descartar | H17: — | I17: — | J17: i5 650 (2010): alto consumo de energia, hardware com 16 anos e risco de falha | K17: =IF(LEFT(G17,12)="Reaproveitar",$B$5,0) -> 0
A18: MARCOS CARVALHO | B18: =_xlfn.XLOOKUP($A18,PlanoMaquinas[Usuário],PlanoMaquinas[Tipo]) -> Desktop | C18: =_xlfn.XLOOKUP($A18,PlanoMaquinas[Usuário],PlanoMaquinas[Processador]) -> INTEL CORE I5 650 | D18: =_xlfn.XLOOKUP($A18,PlanoMaquinas[Usuário],PlanoMaquinas[Memória]) -> 8GB DDR3 | E18: =_xlfn.XLOOKUP($A18,PlanoMaquinas[Usuário],PlanoMaquinas[Ano lanç.]) -> 2010 | F18: =_xlfn.XLOOKUP($A18,PlanoMaquinas[Usuário],PlanoMaquinas[Idade (anos)]) -> 16 | G18: Descartar | H18: — | I18: — | J18: i5 650 (2010): alto consumo de energia, hardware com 16 anos e risco de falha | K18: =IF(LEFT(G18,12)="Reaproveitar",$B$5,0) -> 0
A19: SAC | B19: =_xlfn.XLOOKUP($A19,PlanoMaquinas[Usuário],PlanoMaquinas[Tipo]) -> Desktop | C19: =_xlfn.XLOOKUP($A19,PlanoMaquinas[Usuário],PlanoMaquinas[Processador]) -> INTEL CORE I3 2120 | D19: =_xlfn.XLOOKUP($A19,PlanoMaquinas[Usuário],PlanoMaquinas[Memória]) -> 4GB DDR3 | E19: =_xlfn.XLOOKUP($A19,PlanoMaquinas[Usuário],PlanoMaquinas[Ano lanç.]) -> 2011 | F19: =_xlfn.XLOOKUP($A19,PlanoMaquinas[Usuário],PlanoMaquinas[Idade (anos)]) -> 15 | G19: Descartar | H19: — | I19: — | J19: i3 2120 com apenas 4 GB DDR3: desempenho insuficiente mesmo para uso leve | K19: =IF(LEFT(G19,12)="Reaproveitar",$B$5,0) -> 0
A22: PRÉ-REQUISITOS E CUIDADOS
A23: 1. Sistema operacional | B23: Nenhuma destas máquinas suporta Windows 11. Usar ChromeOS Flex/Linux (gratuitos) ou Windows 10 com ESU pago (até out/2028). Nunca manter Windows 10 sem suporte na rede.
A24: 2. Armazenamento | B24: Trocar HD por SSD em toda máquina reaproveitada (custo em B5).
A25: 3. Dados pessoais (LGPD) | B25: Não usar máquinas reaproveitadas em funções com dados de associados ou financeiros.
A26: 4. Custo x benefício | B26: Reaproveitar não reduz o custo do plano: os usuários atuais recebem máquinas novas. O ganho é cobrir funções extras sem comprar equipamento.
A27: 5. Descarte | B27: Apagar os discos com segurança antes do descarte/doação e destinar a empresa certificada de lixo eletrônico.

Sheet Depreciação Simplificada
A1: SAERJ – Depreciação Simplificada por Máquina (visão Diretoria)
A2: Cada máquina é depreciada em linha reta até R$ 0. O valor mensal é o que deve ser guardado para repor a máquina. Após zerar, cada mês de uso é “lucro” (a máquina trabalha sem custo).
A4: PREMISSAS | B4: Valor | D4: RESUMO PARA A DIRETORIA | H4: Valor
A5: Data de referência | B5: =DATE(2026,9,30) -> 46295 | D5: Valor a guardar por mês (todas as máquinas) | H5: =DeprecSimples[[#Totals],[Guardar por mês (R$)]] -> 2010.4167
A6: Prazo de depreciação – Desktop (meses) | B6: 60 | D6: Valor a guardar por ano (todas as máquinas) | H6: =DeprecSimples[[#Totals],[Guardar por ano (R$)]] -> 24125
A7: Prazo de depreciação – Notebook (meses) | B7: 48 | D7: Máquinas já zeradas (depreciação concluída) | H7: =COUNTIFS(DeprecSimples[Situação],"Zerada") -> 10
A8: Valor de uma máquina nova – Desktop (R$) | B8: ='Plano de Modernização'!B8 -> 4500 | D8: Máquinas ainda em depreciação | H8: =COUNTIFS(DeprecSimples[Situação],"Em depreciação") -> 11
A9: Valor de uma máquina nova – Notebook (R$) | B9: ='Plano de Modernização'!B9 -> 5500 | D9: Saldo ainda a depreciar | H9: =DeprecSimples[[#Totals],[Saldo a depreciar (R$)]] -> 18900
A10: Anos entre lançamento do processador e compra | B10: 1 | D10: “Lucro” acumulado das máquinas zeradas | H10: =DeprecSimples[[#Totals],[“Lucro” após zerar (R$)]] -> 68783.333
A11: Obs.: ano de aquisição estimado pelo processador – substitua pelo ano real da nota fiscal quando disponível (coluna D).
A13: Usuário | B13: Tipo | C13: Processador | D13: Ano de aquisição (est.) | E13: Valor da máquina (R$) | F13: Prazo (meses) | G13: Guardar por mês (R$) | H13: Guardar por ano (R$) | I13: Meses de uso | J13: Valor já depreciado (R$) | K13: Saldo a depreciar (R$) | L13: Zera em | M13: Situação | N13: Meses após zerar | O13: “Lucro” após zerar (R$)
A14: =Planilha1!A4 -> PRISCILA FERNANDES | B14: =IF(Planilha1!E4="DT","Desktop","Notebook") -> Desktop | C14: =Planilha1!B4 -> INTEL I5 650 | D14: =_xlfn.XLOOKUP(A14,PlanoMaquinas[Usuário],PlanoMaquinas[Ano lanç.])+$B$10 -> 2011 | E14: =IF(B14="Desktop",$B$8,$B$9) -> 4500 | F14: =IF(B14="Desktop",$B$6,$B$7) -> 60 | G14: =E14/F14 -> 75 | H14: =G14*12 -> 900 | I14: =DATEDIF(DATE(D14,1,1),$B$5,"m") -> 188 | J14: =MIN(I14,F14)*G14 -> 4500 | K14: =E14-J14 -> 0 | L14: =EDATE(DATE(D14,1,1),F14) -> 42370 | M14: =IF(I14>=F14,"Zerada","Em depreciação") -> Zerada | N14: =MAX(0,I14-F14) -> 128 | O14: =N14*G14 -> 9600
A15: =Planilha1!A5 -> IVANILDE MONTENEGRO | B15: =IF(Planilha1!E5="DT","Desktop","Notebook") -> Desktop | C15: =Planilha1!B5 -> INTEL CORE I5 3470 | D15: =_xlfn.XLOOKUP(A15,PlanoMaquinas[Usuário],PlanoMaquinas[Ano lanç.])+$B$10 -> 2013 | E15: =IF(B15="Desktop",$B$8,$B$9) -> 4500 | F15: =IF(B15="Desktop",$B$6,$B$7) -> 60 | G15: =E15/F15 -> 75 | H15: =G15*12 -> 900 | I15: =DATEDIF(DATE(D15,1,1),$B$5,"m") -> 164 | J15: =MIN(I15,F15)*G15 -> 4500 | K15: =E15-J15 -> 0 | L15: =EDATE(DATE(D15,1,1),F15) -> 43101 | M15: =IF(I15>=F15,"Zerada","Em depreciação") -> Zerada | N15: =MAX(0,I15-F15) -> 104 | O15: =N15*G15 -> 7800
A16: =Planilha1!A6 -> JAQUELINE LESSA | B16: =IF(Planilha1!E6="DT","Desktop","Notebook") -> Desktop | C16: =Planilha1!B6 -> INTEL CORE I5 3470 | D16: =_xlfn.XLOOKUP(A16,PlanoMaquinas[Usuário],PlanoMaquinas[Ano lanç.])+$B$10 -> 2013 | E16: =IF(B16="Desktop",$B$8,$B$9) -> 4500 | F16: =IF(B16="Desktop",$B$6,$B$7) -> 60 | G16: =E16/F16 -> 75 | H16: =G16*12 -> 900 | I16: =DATEDIF(DATE(D16,1,1),$B$5,"m") -> 164 | J16: =MIN(I16,F16)*G16 -> 4500 | K16: =E16-J16 -> 0 | L16: =EDATE(DATE(D16,1,1),F16) -> 43101 | M16: =IF(I16>=F16,"Zerada","Em depreciação") -> Zerada | N16: =MAX(0,I16-F16) -> 104 | O16: =N16*G16 -> 7800
A17: =Planilha1!A7 -> THAMIRES OLIVEIRA | B17: =IF(Planilha1!E7="DT","Desktop","Notebook") -> Notebook | C17: =Planilha1!B7 -> INTEL CORE I5 1334U | D17: =_xlfn.XLOOKUP(A17,PlanoMaquinas[Usuário],PlanoMaquinas[Ano lanç.])+$B$10 -> 2024 | E17: =IF(B17="Desktop",$B$8,$B$9) -> 5500 | F17: =IF(B17="Desktop",$B$6,$B$7) -> 48 | G17: =E17/F17 -> 114.58333 | H17: =G17*12 -> 1375 | I17: =DATEDIF(DATE(D17,1,1),$B$5,"m") -> 32 | J17: =MIN(I17,F17)*G17 -> 3666.6667 | K17: =E17-J17 -> 1833.3333 | L17: =EDATE(DATE(D17,1,1),F17) -> 46753 | M17: =IF(I17>=F17,"Zerada","Em depreciação") -> Em depreciação | N17: =MAX(0,I17-F17) -> 0 | O17: =N17*G17 -> 0
A18: =Planilha1!A8 -> EVELIN CUNHA | B18: =IF(Planilha1!E8="DT","Desktop","Notebook") -> Desktop | C18: =Planilha1!B8 -> INTEL CORE I5 12400 | D18: =_xlfn.XLOOKUP(A18,PlanoMaquinas[Usuário],PlanoMaquinas[Ano lanç.])+$B$10 -> 2023 | E18: =IF(B18="Desktop",$B$8,$B$9) -> 4500 | F18: =IF(B18="Desktop",$B$6,$B$7) -> 60 | G18: =E18/F18 -> 75 | H18: =G18*12 -> 900 | I18: =DATEDIF(DATE(D18,1,1),$B$5,"m") -> 44 | J18: =MIN(I18,F18)*G18 -> 3300 | K18: =E18-J18 -> 1200 | L18: =EDATE(DATE(D18,1,1),F18) -> 46753 | M18: =IF(I18>=F18,"Zerada","Em depreciação") -> Em depreciação | N18: =MAX(0,I18-F18) -> 0 | O18: =N18*G18 -> 0
A19: =Planilha1!A9 -> ISMAEL CAMPELO | B19: =IF(Planilha1!E9="DT","Desktop","Notebook") -> Desktop | C19: =Planilha1!B9 -> INTEL I5 650 | D19: =_xlfn.XLOOKUP(A19,PlanoMaquinas[Usuário],PlanoMaquinas[Ano lanç.])+$B$10 -> 2011 | E19: =IF(B19="Desktop",$B$8,$B$9) -> 4500 | F19: =IF(B19="Desktop",$B$6,$B$7) -> 60 | G19: =E19/F19 -> 75 | H19: =G19*12 -> 900 | I19: =DATEDIF(DATE(D19,1,1),$B$5,"m") -> 188 | J19: =MIN(I19,F19)*G19 -> 4500 | K19: =E19-J19 -> 0 | L19: =EDATE(DATE(D19,1,1),F19) -> 42370 | M19: =IF(I19>=F19,"Zerada","Em depreciação") -> Zerada | N19: =MAX(0,I19-F19) -> 128 | O19: =N19*G19 -> 9600
A20: =Planilha1!A10 -> MARCELO GONÇALVES | B20: =IF(Planilha1!E10="DT","Desktop","Notebook") -> Desktop | C20: =Planilha1!B10 -> INTEL CORE I7 3770 | D20: =_xlfn.XLOOKUP(A20,PlanoMaquinas[Usuário],PlanoMaquinas[Ano lanç.])+$B$10 -> 2013 | E20: =IF(B20="Desktop",$B$8,$B$9) -> 4500 | F20: =IF(B20="Desktop",$B$6,$B$7) -> 60 | G20: =E20/F20 -> 75 | H20: =G20*12 -> 900 | I20: =DATEDIF(DATE(D20,1,1),$B$5,"m") -> 164 | J20: =MIN(I20,F20)*G20 -> 4500 | K20: =E20-J20 -> 0 | L20: =EDATE(DATE(D20,1,1),F20) -> 43101 | M20: =IF(I20>=F20,"Zerada","Em depreciação") -> Zerada | N20: =MAX(0,I20-F20) -> 104 | O20: =N20*G20 -> 7800
A21: =Planilha1!A11 -> FABRICIO MEDEIROS | B21: =IF(Planilha1!E11="DT","Desktop","Notebook") -> Notebook | C21: =Planilha1!B11 -> INTEL CORE I7 1165G7 | D21: =_xlfn.XLOOKUP(A21,PlanoMaquinas[Usuário],PlanoMaquinas[Ano lanç.])+$B$10 -> 2021 | E21: =IF(B21="Desktop",$B$8,$B$9) -> 5500 | F21: =IF(B21="Desktop",$B$6,$B$7) -> 48 | G21: =E21/F21 -> 114.58333 | H21: =G21*12 -> 1375 | I21: =DATEDIF(DATE(D21,1,1),$B$5,"m") -> 68 | J21: =MIN(I21,F21)*G21 -> 5500 | K21: =E21-J21 -> 0 | L21: =EDATE(DATE(D21,1,1),F21) -> 45658 | M21: =IF(I21>=F21,"Zerada","Em depreciação") -> Zerada | N21: =MAX(0,I21-F21) -> 20 | O21: =N21*G21 -> 2291.6667
A22: =Planilha1!A12 -> ANDRÉ MANHÃES | B22: =IF(Planilha1!E12="DT","Desktop","Notebook") -> Desktop | C22: =Planilha1!B12 -> INTEL CORE I5 7400 | D22: =_xlfn.XLOOKUP(A22,PlanoMaquinas[Usuário],PlanoMaquinas[Ano lanç.])+$B$10 -> 2018 | E22: =IF(B22="Desktop",$B$8,$B$9) -> 4500 | F22: =IF(B22="Desktop",$B$6,$B$7) -> 60 | G22: =E22/F22 -> 75 | H22: =G22*12 -> 900 | I22: =DATEDIF(DATE(D22,1,1),$B$5,"m") -> 104 | J22: =MIN(I22,F22)*G22 -> 4500 | K22: =E22-J22 -> 0 | L22: =EDATE(DATE(D22,1,1),F22) -> 44927 | M22: =IF(I22>=F22,"Zerada","Em depreciação") -> Zerada | N22: =MAX(0,I22-F22) -> 44 | O22: =N22*G22 -> 3300
A23: =Planilha1!A13 -> FELIPE FACHETTI | B23: =IF(Planilha1!E13="DT","Desktop","Notebook") -> Notebook | C23: =Planilha1!B13 -> INTEL CORE I5 1334U | D23: =_xlfn.XLOOKUP(A23,PlanoMaquinas[Usuário],PlanoMaquinas[Ano lanç.])+$B$10 -> 2024 | E23: =IF(B23="Desktop",$B$8,$B$9) -> 5500 | F23: =IF(B23="Desktop",$B$6,$B$7) -> 48 | G23: =E23/F23 -> 114.58333 | H23: =G23*12 -> 1375 | I23: =DATEDIF(DATE(D23,1,1),$B$5,"m") -> 32 | J23: =MIN(I23,F23)*G23 -> 3666.6667 | K23: =E23-J23 -> 1833.3333 | L23: =EDATE(DATE(D23,1,1),F23) -> 46753 | M23: =IF(I23>=F23,"Zerada","Em depreciação") -> Em depreciação | N23: =MAX(0,I23-F23) -> 0 | O23: =N23*G23 -> 0
A24: =Planilha1!A14 -> ALEXANDRO NASCIMENTO | B24: =IF(Planilha1!E14="DT","Desktop","Notebook") -> Notebook | C24: =Planilha1!B14 -> INTEL CORE I7 1165G7 | D24: =_xlfn.XLOOKUP(A24,PlanoMaquinas[Usuário],PlanoMaquinas[Ano lanç.])+$B$10 -> 2021 | E24: =IF(B24="Desktop",$B$8,$B$9) -> 5500 | F24: =IF(B24="Desktop",$B$6,$B$7) -> 48 | G24: =E24/F24 -> 114.58333 | H24: =G24*12 -> 1375 | I24: =DATEDIF(DATE(D24,1,1),$B$5,"m") -> 68 | J24: =MIN(I24,F24)*G24 -> 5500 | K24: =E24-J24 -> 0 | L24: =EDATE(DATE(D24,1,1),F24) -> 45658 | M24: =IF(I24>=F24,"Zerada","Em depreciação") -> Zerada | N24: =MAX(0,I24-F24) -> 20 | O24: =N24*G24 -> 2291.6667
A25: =Planilha1!A15 -> SAC | B25: =IF(Planilha1!E15="DT","Desktop","Notebook") -> Desktop | C25: =Planilha1!B15 -> INTEL CORE I3 2120 | D25: =_xlfn.XLOOKUP(A25,PlanoMaquinas[Usuário],PlanoMaquinas[Ano lanç.])+$B$10 -> 2012 | E25: =IF(B25="Desktop",$B$8,$B$9) -> 4500 | F25: =IF(B25="Desktop",$B$6,$B$7) -> 60 | G25: =E25/F25 -> 75 | H25: =G25*12 -> 900 | I25: =DATEDIF(DATE(D25,1,1),$B$5,"m") -> 176 | J25: =MIN(I25,F25)*G25 -> 4500 | K25: =E25-J25 -> 0 | L25: =EDATE(DATE(D25,1,1),F25) -> 42736 | M25: =IF(I25>=F25,"Zerada","Em depreciação") -> Zerada | N25: =MAX(0,I25-F25) -> 116 | O25: =N25*G25 -> 8700
... A34: =Planilha1!A24 -> MARCELO REBELO | B34: =IF(Planilha1!E24="DT","Desktop","Notebook") -> Notebook | C34: =Planilha1!B24 -> INTEL CORE I5 1334U | D34: =_xlfn.XLOOKUP(A34,PlanoMaquinas[Usuário],PlanoMaquinas[Ano lanç.])+$B$10 -> 2024 | E34: =IF(B34="Desktop",$B$8,$B$9) -> 5500 | F34: =IF(B34="Desktop",$B$6,$B$7) -> 48 | G34: =E34/F34 -> 114.58333 | H34: =G34*12 -> 1375 | I34: =DATEDIF(DATE(D34,1,1),$B$5,"m") -> 32 | J34: =MIN(I34,F34)*G34 -> 3666.6667 | K34: =E34-J34 -> 1833.3333 | L34: =EDATE(DATE(D34,1,1),F34) -> 46753 | M34: =IF(I34>=F34,"Zerada","Em depreciação") -> Em depreciação | N34: =MAX(0,I34-F34) -> 0 | O34: =N34*G34 -> 0
A35: Total | E35: =SUBTOTAL(109,DeprecSimples[Valor da máquina (R$)]) -> 105500 | G35: =SUBTOTAL(109,DeprecSimples[Guardar por mês (R$)]) -> 2010.4167 | H35: =SUBTOTAL(109,DeprecSimples[Guardar por ano (R$)]) -> 24125 | J35: =SUBTOTAL(109,DeprecSimples[Valor já depreciado (R$)]) -> 86600 | K35: =SUBTOTAL(109,DeprecSimples[Saldo a depreciar (R$)]) -> 18900 | O35: =SUBTOTAL(109,DeprecSimples[“Lucro” após zerar (R$)]) -> 68783.333
